seisnn/__init__.py
seisnn/components.py
seisnn/core.py
seisnn/example_proto.py
seisnn/io.py
seisnn/logger.py
seisnn/plot.py
seisnn/qc.py
seisnn/sql.py
seisnn/ui.py
seisnn/utils.py
SeisBlue-0.0.1.dev1.dist-info/LICENSE
SeisBlue-0.0.1.dev1.dist-info/METADATA
SeisBlue-0.0.1.dev1.dist-info/WHEEL
SeisBlue-0.0.1.dev1.dist-info/top_level.txt
SeisBlue-0.0.1.dev1.dist-info/RECORD
